Workbook

Sheet Dashboard
B2: R & D LAB MANAGEMENT DASHBOARD
B4: Materials • Testing • Casting • Resources • Budget
B6: TOTAL MATERIALS | F6: CASTING ACTIVITIES | J6: TOTAL TESTS | N6: CRITICAL MATERIALS | R6: TOTAL BUDGET
B7: =SUMPRODUCT(('Materials & Inventory'!D13:D5000<>"")/COUNTIF('Materials & Inventory'!D13:D5000,'Materials & Inventory'!D13:D5000&"")) -> 5 | F7: =COUNTIF('Casting and Testing Activity'!B28:B5000,TODAY()) -> 1 | J7: =COUNTIF('Flow Table Test '!B5:B1048576,TODAY())+COUNTIF('Compression Test '!B5:B1048576,TODAY())+COUNTIF('Flexural Test '!B4:B1048576,TODAY()) -> 0 | N7: =COUNTIF('Materials & Inventory'!O:O,"Critical") -> 3 | R7: =Budget!D6 -> 48342719
A30: Material To Buy
L31: Budget Status
B33: S. No | C33: Material | I33: Total Budget | L33: Utilized | O33: Balance
B34: 1 | C34: =IFERROR(INDEX('Materials & Inventory'!$D$13:$D$5000,_xlfn.AGGREGATE(15,6,(ROW('Materials & Inventory'!$D$13:$D$5000)-ROW('Materials & Inventory'!$D$13)+1)/(('Materials & Inventory'!$O$13:$O$5000="Critical")*(COUNTIF($C$33:C33,'Materials & Inventory'!$D$13:$D$5000)=0)),1)),"") -> OPC 53 | I34: =Budget!D6 -> 48342719 | L34: 16800000 | O34: =I34-L34 -> 31542719
B35: 2 | C35: =IFERROR(INDEX('Materials & Inventory'!$D$13:$D$5000,_xlfn.AGGREGATE(15,6,(ROW('Materials & Inventory'!$D$13:$D$5000)-ROW('Materials & Inventory'!$D$13)+1)/(('Materials & Inventory'!$O$13:$O$5000="Critical")*(COUNTIF($C$33:C34,'Materials & Inventory'!$D$13:$D$5000)=0)),1)),"") -> Flyash
B36: 3 | C36: =IFERROR(INDEX('Materials & Inventory'!$D$13:$D$5000,_xlfn.AGGREGATE(15,6,(ROW('Materials & Inventory'!$D$13:$D$5000)-ROW('Materials & Inventory'!$D$13)+1)/(('Materials & Inventory'!$O$13:$O$5000="Critical")*(COUNTIF($C$33:C35,'Materials & Inventory'!$D$13:$D$5000)=0)),1)),"")
C37: =IFERROR(INDEX('Materials & Inventory'!$D$13:$D$5000,_xlfn.AGGREGATE(15,6,(ROW('Materials & Inventory'!$D$13:$D$5000)-ROW('Materials & Inventory'!$D$13)+1)/('Materials & Inventory'!$O$13:$O$5000="Critical"),ROWS($C$33:C36))),"") | M37: Budget Utilization
C38: =IFERROR(INDEX('Materials & Inventory'!$D$13:$D$5000,_xlfn.AGGREGATE(15,6,(ROW('Materials & Inventory'!$D$13:$D$5000)-ROW('Materials & Inventory'!$D$13)+1)/('Materials & Inventory'!$O$13:$O$5000="Critical"),ROWS($C$33:C37))),"")
C39: =IFERROR(INDEX('Materials & Inventory'!$D$13:$D$5000,_xlfn.AGGREGATE(15,6,(ROW('Materials & Inventory'!$D$13:$D$5000)-ROW('Materials & Inventory'!$D$13)+1)/('Materials & Inventory'!$O$13:$O$5000="Critical"),ROWS($C$33:C38))),"")
C40: =IFERROR(INDEX('Materials & Inventory'!$D$13:$D$5000,_xlfn.AGGREGATE(15,6,(ROW('Materials & Inventory'!$D$13:$D$5000)-ROW('Materials & Inventory'!$D$13)+1)/('Materials & Inventory'!$O$13:$O$5000="Critical"),ROWS($C$33:C39))),"") | M40: =L34/I34 -> 0.34751872
C41: =IFERROR(INDEX('Materials & Inventory'!$D$13:$D$5000,_xlfn.AGGREGATE(15,6,(ROW('Materials & Inventory'!$D$13:$D$5000)-ROW('Materials & Inventory'!$D$13)+1)/('Materials & Inventory'!$O$13:$O$5000="Critical"),ROWS($C$33:C40))),"")
C42: =IFERROR(INDEX('Materials & Inventory'!$D$13:$D$5000,_xlfn.AGGREGATE(15,6,(ROW('Materials & Inventory'!$D$13:$D$5000)-ROW('Materials & Inventory'!$D$13)+1)/('Materials & Inventory'!$O$13:$O$5000="Critical"),ROWS($C$33:C40))),"")

Sheet Sheet2
I11: =Dashboard!L34/Dashboard!I34 -> 0.34751872
I12: =1-Dashboard!M40 -> 0.65248128
B13: Status | C13: Count | E13: Test | F13: No of Test
B14: Adequate | C14: =COUNTIF('Materials & Inventory'!O13:O1048576,"Adequate") -> 6 | E14: Compression | F14: =COUNTA('Compression Test '!B5:B1048576) -> 5
B15: Low | C15: =COUNTIF('Materials & Inventory'!O13:O1048576,"Low") -> 0 | E15: Flexural Test | F15: =COUNTA('Flexural Test '!B4:B1048576) -> 5
B16: Critical | C16: =COUNTIF('Materials & Inventory'!O13:O1048576,"Critical") -> 3 | E16: Flow Test | F16: =COUNTA('Flow Table Test '!B5:B1048576) -> 5

Sheet Materials & Inventory
A1: Materials & Inventory
B7: =SUMPRODUCT(('Materials & Inventory'!D13:D5003<>"")/COUNTIF('Materials & Inventory'!D13:D5003,'Materials & Inventory'!D13:D5003&"")) -> 5 | E7: =COUNTIF(O13:O1003,"Low")+COUNTIF(O13:O1003,"Critical") -> 3 | I7: =COUNTIF(P7:P1003,"Yes") -> 3 | L7: =COUNTIF(Q12:Q1003,"Urgent") -> 3
U10: =COUNTA(Table1[Category]) -> 8
A12: S.No | B12: Date | C12: Material ID | D12: Material | E12: Category | F12: Supplier | G12: Unit | H12: Opening Stock | I12: Received | J12: Consumed | K12: Closing Stock | L12: Minimum Stock | M12: Required Stock | N12: Order Quantity | O12: Stock Status | P12: Purchase Required | Q12: Purchase Priority | R12: Remarks
A13: 1 | B13: 46266 | C13: CEM001 | D13: OPC 53 | E13: Cement | F13: ABC Cement | G13: kg | H13: 100 | I13: 200 | J13: 150 | K13: =(H13+I13)-J13 -> 150 | L13: 200 | M13: 500 | N13: =MAX(0,M13-K13) -> 350 | O13: =IF(K13<L13,"Critical",IF(Table1[[#This Row],[Closing Stock]]<Table1[[#This Row],[Required Stock]],"Low","Adequate")) -> Critical | P13: =IF(K13<M13,"Yes","No") -> Yes | Q13: =IF(K13<L13,"Urgent",IF(K13<M13,"Normal","-")) -> Urgent | R13: —
A14: 2 | B14: 46266 | C14: CEM002 | D14: Flyash | E14: SCM's | F14: ABC Cement | G14: kg | H14: 100 | I14: 0 | J14: 180 | K14: =(H14+I14)-J14 -> -80 | L14: 200 | M14: 500 | N14: =MAX(0,M14-K14) -> 580 | O14: =IF(K14<L14,"Critical",IF(Table1[[#This Row],[Closing Stock]]<Table1[[#This Row],[Required Stock]],"Low","Adequate")) -> Critical | P14: =IF(K14<M14,"Yes","No") -> Yes | Q14: =IF(K14<L14,"Urgent",IF(K14<M14,"Normal","-")) -> Urgent | R14: Reorder
A15: 3 | B15: 46266 | C15: CEM003 | D15: GGBS | E15: SCM's | F15: ABC Cement | G15: kg | H15: 370 | I15: 300 | J15: 100 | K15: =(H15+I15)-J15 -> 570 | L15: 200 | M15: 500 | N15: =MAX(0,M15-K15) -> 0 | O15: =IF(K15<L15,"Critical",IF(Table1[[#This Row],[Closing Stock]]<Table1[[#This Row],[Required Stock]],"Low","Adequate")) -> Adequate | P15: =IF(K15<M15,"Yes","No") -> No | Q15: =IF(K15<L15,"Urgent",IF(K15<M15,"Normal","-")) -> - | R15: —
A16: 4 | B16: 46266 | C16: CEM004 | D16: Super Plastizier | E16: Admixture | G16: kg | K16: =(H16+I16)-J16 -> 0 | N16: =MAX(0,M16-K16) -> 0 | O16: =IF(K16<L16,"Critical",IF(Table1[[#This Row],[Closing Stock]]<Table1[[#This Row],[Required Stock]],"Low","Adequate")) -> Adequate | P16: =IF(K16<M16,"Yes","No") -> No | Q16: =IF(K16<L16,"Urgent",IF(K16<M16,"Normal","-")) -> -
A17: 5 | B17: 46266 | C17: CEM005 | D17: Steel Fibres | G17: kg | K17: =(H17+I17)-J17 -> 0 | N17: =MAX(0,M17-K17) -> 0 | O17: =IF(K17<L17,"Critical",IF(Table1[[#This Row],[Closing Stock]]<Table1[[#This Row],[Required Stock]],"Low","Adequate")) -> Adequate | P17: =IF(K17<M17,"Yes","No") -> No | Q17: =IF(K17<L17,"Urgent",IF(K17<M17,"Normal","-")) -> -
A18: 6 | B18: 46267 | D18: OPC 53 | E18: Cement | G18: kg | H18: =IFERROR(SUMIFS(Table1[Closing Stock],Table1[Material],Table1[[#This Row],[Material]],Table1[Date],Table1[[#This Row],[Date]]-1),"") -> 150 | K18: =(H18+I18)-J18 -> 150 | N18: =MAX(0,M18-K18) -> 0 | O18: =IF(K18<L18,"Critical",IF(Table1[[#This Row],[Closing Stock]]<Table1[[#This Row],[Required Stock]],"Low","Adequate")) -> Adequate | P18: =IF(K18<M18,"Yes","No") -> No | Q18: =IF(K18<L18,"Urgent",IF(K18<M18,"Normal","-")) -> -
B19: 46267 | D19: Flyash | E19: SCM's | G19: kg | H19: =IFERROR(SUMIFS(Table1[Closing Stock],Table1[Material],Table1[[#This Row],[Material]],Table1[Date],Table1[[#This Row],[Date]]-1),"") -> -80 | K19: =(H19+I19)-J19 -> -80 | N19: =MAX(0,M19-K19) -> 80 | O19: =IF(K19<L19,"Critical",IF(Table1[[#This Row],[Closing Stock]]<Table1[[#This Row],[Required Stock]],"Low","Adequate")) -> Critical | P19: =IF(K19<M19,"Yes","No") -> Yes | Q19: =IF(K19<L19,"Urgent",IF(K19<M19,"Normal","-")) -> Urgent
B20: 46267 | D20: GGBS | E20: SCM's | G20: kg | H20: =IFERROR(SUMIFS(Table1[Closing Stock],Table1[Material],Table1[[#This Row],[Material]],Table1[Date],Table1[[#This Row],[Date]]-1),"") -> 570 | K20: =(H20+I20)-J20 -> 570 | N20: =MAX(0,M20-K20) -> 0 | O20: =IF(K20<L20,"Critical",IF(Table1[[#This Row],[Closing Stock]]<Table1[[#This Row],[Required Stock]],"Low","Adequate")) -> Adequate | P20: =IF(K20<M20,"Yes","No") -> No | Q20: =IF(K20<L20,"Urgent",IF(K20<M20,"Normal","-")) -> -
B21: 46267 | D21: Super Plastizier | E21: Admixture | G21: kg | H21: =IFERROR(SUMIFS(Table1[Closing Stock],Table1[Material],Table1[[#This Row],[Material]],Table1[Date],Table1[[#This Row],[Date]]-1),"") -> 0 | K21: =(H21+I21)-J21 -> 0 | N21: =MAX(0,M21-K21) -> 0 | O21: =IF(K21<L21,"Critical",IF(Table1[[#This Row],[Closing Stock]]<Table1[[#This Row],[Required Stock]],"Low","Adequate")) -> Adequate | P21: =IF(K21<M21,"Yes","No") -> No | Q21: =IF(K21<L21,"Urgent",IF(K21<M21,"Normal","-")) -> -
B29: =B29:B30 -> 0

Sheet Human Resources 
B1: Human Resources
A5: S.No | B5: Date | C5: Employee Name | D5: Designation | E5: work Category | F5: Task | G5: Description | H5: Start Time | I5: End Time | J5: Task Status | K5: output/ Result | L5: Issue / Problem | M5: Corrective Action | N5: Supervisor | O5: Remarks | P5: Column1 | Q5: Column2 | R5: Column3
A6: =ROW() - ROW(Table13[[#Headers],[S.No]]) -> 1 | C6: Dr. Revanth Kumar
A7: =ROW() - ROW(Table13[[#Headers],[S.No]]) -> 2 | C7: Dr. Anand Raj
A8: =ROW() - ROW(Table13[[#Headers],[S.No]]) -> 3 | C8: Mirityun
A9: =ROW() - ROW(Table13[[#Headers],[S.No]]) -> 4 | C9: Neeraj
A10: =ROW() - ROW(Table13[[#Headers],[S.No]]) -> 5 | C10: Siva sri
A11: 6 | C11: Yazhini

Sheet Casting and Testing Activity
A3: MIX ID
A7: S.No | B7: Mix ID | C7: Date | D7: Target Flow (mm) | E7: Target Compressive Strength | F7: Target Flexural Strength | G7: Status | H7: Remarks
B21: Casting And Testing Activity
A27: S.No | B27: Date | C27: Mix ID | D27: Batch No | E27: Target Volume | F27: Actual Volume | G27: Cement | H27: Silica Fume | I27: GGBS | J27: Limestone Powder | K27: Quartz Powder/ Sand | L27: Water | M27: Superplasticizer | N27: SRA | O27: Fibre | P27: Total Binder | Q27: W/b Ratio | R27: SP Dosage | S27: Fibre Volume % | T27: Mixing Start Time | U27: Mixing End Time | V27: Humidity | W27: Mixing Duration | X27: Casting Start | Y27: Cast Completion | Z27: Number Of Specimen | AA27: Mould Type | AB27: Demoulding Date | AC27: Curing Method | AD27: Curing Temperature | AE27: Responsible ET | AF27: Observation | AG27: Remarks
A28: 1 | B28: 46272 | D28: 1
A29: 2 | B29: 46273 | D29: 2
A30: 3 | B30: 46274 | D30: 3

Sheet Flow Table Test 
B1: Flow Table Test
A4: S.No | B4: Date | C4: Trail ID | D4: Mix ID | E4: Test Standard | F4: Ambient Temperature | G4: UHPC Temperature | H4: d1 (mm) | I4: d2(mm) | J4: D1-D2 | K4: Average speed = (d1+d2)/2 (mm) | L4: Flow Table (mm) | M4: Stabilization Time | N4: Segregation | O4: w/b Ratio | P4: SP Dosage | Q4: SRA Dosage | R4: Humidity
A5: =ROW() - ROW(Table134[[#Headers],[S.No]]) -> 1 | B5: 46266
A6: =ROW() - ROW(Table134[[#Headers],[S.No]]) -> 2 | B6: 46267
A7: =ROW() - ROW(Table134[[#Headers],[S.No]]) -> 3 | B7: 46268
A8: =ROW() - ROW(Table134[[#Headers],[S.No]]) -> 4 | B8: 46269
A9: =ROW() - ROW(Table134[[#Headers],[S.No]]) -> 5 | B9: 46270

Sheet Compression Test 
B1: Compressive Strength Test
A4: S.No | B4: Date | C4: Test ID | D4: Time | E4: Mix ID | F4: Batch ID | G4: Specimen ID | H4: Test Standard | I4: Casting Date | J4: Target Age | K4: Actual Age | L4: Curing Temperature | M4: Testing Temperature | N4: Specimen Type | O4: Nominal Length | P4: Nominal Width | Q4: Nominal Height | R4: Measured Length | S4: Mesured Width | T4: Measured Height | U4: Diameter ( cylindrical Specimen ) | V4: Cross sectional Area | W4: Loading Rate (Mpa/s) | X4: Maximum Load (KN) | Y4: Failure Type | Z4: Faliure Observation | AA4: Compressive Strength Mpa | AB4: Target Strength Mpa | AC4: Remarks
A5: =ROW() - ROW(Table1345[[#Headers],[S.No]]) -> 1 | B5: 46266
A6: =ROW() - ROW(Table1345[[#Headers],[S.No]]) -> 2 | B6: 46267
A7: =ROW() - ROW(Table1345[[#Headers],[S.No]]) -> 3 | B7: 46268
A8: =ROW() - ROW(Table1345[[#Headers],[S.No]]) -> 4 | B8: 46269
A9: =ROW() - ROW(Table1345[[#Headers],[S.No]]) -> 5 | B9: 46270

Sheet Flexural  Test 
A3: S.No | B3: Date | C3: Test ID | D3: Mix ID | E3: Batch ID | F3: Specimen ID | G3: Test Standard | H3: Test Type | I3: Casting Date | J3: Target Age | K3: Actual Age | L3: Curing Temperature | M3: Testing Temperature | N3: Specimen Type | O3: Notched /Unnotched | P3: Length (mm) | Q3: Width (mm) | R3: Height (mm) | S3: Fibre Type | T3: Fibre Length (mm) | U3: Fibre Volume (%) | V3: Notch Depth (mm) | W3: Notch Width (mm) | X3: Support Span (mm) | Y3: Loading Direction | Z3: Loading Rate (mm/min) | AA3: First Crack Load (KN) | AB3: First Crack Deflection (mm) | AC3: First Crack Stress (Mpa) | AE3: Peak Load (KN) | AF3: Peak Deflection (mm) | AG3: Crack Opening at Peak (mm) | AH3: Flexuarl Strength (Mpa) | AI3: Residual Strength (Mpa) | AJ3: Ultimate Deflection (mm) | AK3: Toughness (j) | AL3: Failure Mode | AM3: Remarks
A4: =ROW() - ROW(Table134510[[#Headers],[S.No]]) -> 1 | B4: 46266
A5: =ROW() - ROW(Table134510[[#Headers],[S.No]]) -> 2 | B5: 46267
A6: =ROW() - ROW(Table134510[[#Headers],[S.No]]) -> 3 | B6: 46268
A7: =ROW() - ROW(Table134510[[#Headers],[S.No]]) -> 4 | B7: 46269
A8: =ROW() - ROW(Table134510[[#Headers],[S.No]]) -> 5 | B8: 46270

Sheet Budget
C1: Summary Bangalore Plant Capex for Approval
C3: Cost Head | D3: Basic Amount | E3: GST@18%
C4: Civil Work | D4: 65572779 | E4: 11803100
C5: Plant & Machinery | D5: 73091625 | E5: 13156493
C6: R&D Center | D6: 48342719 | E6: 8701689
C7: Consultancy | D7: 4500000 | E7: 810000
C8: Misc (Store, Labour Qtrs, etc) | D8: 8059200 | E8: 1450656
C9: Sub - Total | D9: 199566323 | E9: 35921938
C10: Land Value | D10: 101250000
C11: Pre Operative Expense | D11: 63600000
C12: Total | D12: 364416323 | E12: 35921938
C15: R&D Center Budget Details
C17: S.No | D17: Lab equipment | E17: No's | F17: Basic | H17: gst(18%) | I17: total
C18: 1 | D18: Compression Testing M/c-FTM-3000/350kN | E18: 1 | F18: 23717676 | G18: 23717676 | H18: 4269181.8 | I18: 27986858
C19: 2 | D19: Sieve Shaker | E19: 1 | F19: 143000 | G19: 143000 | H19: 25740 | I19: 168740
C20: 3 | D20: Microwave oven | E20: 1 | F20: 8690 | G20: 8690 | H20: 1564.2 | I20: 10254.2
C21: 4 | D21: Mortar Mixer-5 Liter | E21: 1 | F21: 536000 | G21: 536000 | H21: 96480 | I21: 632480
C22: 5 | D22: Mortar Mixer-20 Liter | E22: 1 | F22: 409200 | G22: 409200 | H22: 73656 | I22: 482856
C23: 6 | D23: Concrete Mixer-Pan | E23: 1 | F23: 205500 | G23: 205500 | H23: 36990 | I23: 242490
C24: 7 | D24: Concrete Grinding Machine | E24: 1 | F24: 2035000 | G24: 2035000 | H24: 366300 | I24: 2401300
C25: 8 | D25: Automatic Vicat Apparatus | E25: 1 | F25: 629521 | G25: 629521.2 | H25: 113313.8 | I25: 742835.02
C26: 9 | D26: V Funnel Apparatus | E26: 1 | F26: 4000 | G26: 4000 | H26: 720 | I26: 4720
C27: 10 | D27: Humidity Chamber | E27: 1 | F27: 356366 | G27: 356365.9 | H27: 64145.9 | I27: 420511.76
C28: 11 | D28: Curing tank | E28: 1 | F28: 376000 | G28: 376000 | H28: 67680 | I28: 443680
C29: 12 | D29: Dust Extraction/Ventilation | E29: 1 | F29: 123000 | G29: 123000 | H29: 22140 | I29: 145140
... C40: 23 | D40: Muffle furnace | E40: 1 | F40: 201000 | G40: 201000 | H40: 36180 | I40: 237180
C41: 24 | D41: Interior design | F41: 5500000 | G41: 5500000 | H41: 990000 | I41: 6490000
C42: 25 | D42: Curing Tank ( Heat Cool ) | E42: 2 | F42: 625000 | G42: 1250000 | H42: 225000 | I42: 1475000
C43: 26 | D43: ASR Moulds | E43: 9 | F43: 20000 | G43: 180000 | H43: 32400 | I43: 212400
D45: Total | G45: 36342718 | H45: 6541689.3 | I45: 42884408

Sheet SCM
A1: SCM Equipments and Instruments
A4: S.No | B4: Item Code | C4: Item Description | D4: HSN | E4: Supplier / Vendor | F4: Delivery Date | G4: Qty | H4: UOM | I4: Rate (₹) | J4: Tax | K4: Purchase Req. | L4: Line Item | M4: Amount (₹) | N4: PO No. | O4: Received Qty | P4: Pending Qty | Q4: Actual Delivery Date | R4: Purchase Status
A5: 1 | B5: 8507145 | C5: PVC Cube Mould – 50 × 50 × 50 | D5: 39269099 | E5: — | F5: 46243 | G5: 55 | H5: NOS | I5: 375 | J5: IGST 18% | K5: 230000339 | L5: 1/420 | M5: 20625 | N5: — | O5: — | P5: — | Q5: — | R5: Ordered
A6: 2 | B6: 8507144 | C6: Plastic Mould – 100 × 100 × 100 mm | D6: 39269099 | E6: — | F6: 46243 | G6: 55 | H6: NOS | I6: 625 | J6: IGST 18% | K6: 230000339 | L6: 1/410 | M6: 34375 | N6: — | O6: — | P6: — | Q6: — | R6: Ordered
A7: 3 | B7: 8507150 | C7: Beam Mould – 100 × 100 × 500 mm | D7: 84806000 | E7: — | F7: 46243 | G7: 3 | H7: NOS | I7: 3700 | J7: IGST 18% | K7: 230000339 | L7: 1/460 | M7: 11100 | N7: — | O7: — | P7: — | Q7: — | R7: Ordered
A8: 4 | B8: 8507146 | C8: Cube Mould – 40 × 40 × 160 | D8: 84806000 | E8: — | F8: 46243 | G8: 3 | H8: NOS | I8: 2700 | J8: IGST 18% | K8: 230000339 | L8: 1/430 | M8: 8100 | N8: — | O8: — | P8: — | Q8: — | R8: Ordered
A9: 5 | B9: — | C9: Twin Shaft Mixer – UHPC Purpose Operated through Servo Motor | D9: — | E9: BHS / Elba | F9: 46295 | G9: 1 | H9: NOS | I9: — | J9: — | K9: 2300003390 | L9: 10 | M9: 1600000 | N9: 3500003227 | O9: — | P9: — | Q9: — | R9: PO Released
A10: 6 | B10: — | C10: Compression Testing Machine | D10: — | E10: KAIZEN | F10: 46254 | G10: 1 | H10: NOS | I10: — | J10: — | K10: 2300003390 | L10: 20 | M10: 495000 | N10: 3500003230 | O10: — | P10: — | Q10: — | R10: PO Released
A11: 7 | B11: — | C11: Compression Testing Machine – Flexure Option / Servo Valve | D11: — | E11: Controls / Testing | F11: 46381 | G11: 1 | H11: NOS | I11: — | J11: — | K11: 2300003390 | L11: — | M11: — | N11: — | O11: — | P11: — | Q11: — | R11: In Approval
A12: 8 | B12: — | C12: Muffle Furnace | D12: — | E12: Srintha Scientific | F12: — | G12: 1 | H12: NOS | I12: — | J12: — | K12: 2300003501 | L12: 10 | M12: 195000 | N12: — | O12: — | P12: — | Q12: — | R12: Revised PR Pending
A13: 9 | B13: — | C13: Vibro Sieve Shaker – Sand Segregation | D13: — | E13: JS Vibro | F13: — | G13: 1 | H13: NOS | I13: — | J13: — | K13: 2300003391 | L13: 20 | M13: 130000 | N13: — | O13: — | P13: — | Q13: — | R13: In Audit
A14: 10 | B14: — | C14: Microwave Oven | D14: — | E14: Moglix / LG | F14: — | G14: 1 | H14: NOS | I14: — | J14: — | K14: 2300003391 | L14: 30 | M14: 7900 | N14: — | O14: — | P14: — | Q14: — | R14: Revised PR Pending
A15: 11 | B15: — | C15: Hot Air Oven | D15: — | E15: Sai Krishna | F15: 46245 | G15: 1 | H15: NOS | I15: — | J15: — | K15: 2300003391 | L15: 40 | M15: 43650 | N15: 3500003266 | O15: — | P15: — | Q15: — | R15: PO Released
A16: 12 | B16: — | C16: Pycnometer Bottles – Binders and Aggregates | D16: — | E16: Sai Krishna | F16: 46245 | G16: 1 | H16: NOS | I16: — | J16: — | K16: 2300003391 | L16: 50 | M16: 610 | N16: 3500003266 | O16: — | P16: — | Q16: — | R16: PO Released
A17: 13 | B17: — | C17: Sieve Brass Frame 20 cm × 4.75 mm | D17: — | E17: Sai Krishna | F17: 46245 | G17: 1 | H17: NOS | I17: — | J17: — | K17: 2300003391 | L17: 60 | M17: 675 | N17: 3500003266 | O17: — | P17: — | Q17: — | R17: PO Released
A18: 14 | B18: — | C18: Sieve Brass Frame 20 cm × 2.36 mm | D18: — | E18: Sai Krishna | F18: 46245 | G18: 1 | H18: NOS | I18: — | J18: — | K18: 2300003391 | L18: 70 | M18: 675 | N18: 3500003266 | O18: — | P18: — | Q18: — | R18: PO Released
A19: 15 | B19: — | C19: Sieve Brass Frame 20 cm × 1.18 mm | D19: — | E19: Sai Krishna | F19: 46245 | G19: 1 | H19: NOS | I19: — | J19: — | K19: 2300003391 | L19: 80 | M19: 675 | N19: 3500003266 | O19: — | P19: — | Q19: — | R19: PO Released
A20: 16 | B20: — | C20: Sieve Brass Frame 20 cm × 600 microns | D20: — | E20: Sai Krishna | F20: 46245 | G20: 1 | H20: NOS | I20: — | J20: — | K20: 2300003391 | L20: 90 | M20: 675 | N20: 3500003266 | O20: — | P20: — | Q20: — | R20: PO Released
A21: 17 | B21: — | C21: Sieve Brass Frame 20 cm × 300 microns | D21: — | E21: Sai Krishna | F21: 46245 | G21: 1 | H21: NOS | I21: — | J21: — | K21: 2300003391 | L21: 100 | M21: 675 | N21: 3500003266 | O21: — | P21: — | Q21: — | R21: PO Released
A22: 18 | B22: — | C22: Sieve Brass Frame 20 cm × 150 microns | D22: — | E22: Sai Krishna | F22: 46245 | G22: 1 | H22: NOS | I22: — | J22: — | K22: 2300003391 | L22: 110 | M22: 675 | N22: 3500003266 | O22: — | P22: — | Q22: — | R22: PO Released
A23: 19 | B23: — | C23: Sieve Brass Frame 20 cm × 75 microns | D23: — | E23: Sai Krishna | F23: 46245 | G23: 1 | H23: NOS | I23: — | J23: — | K23: 2300003391 | L23: 120 | M23: 765 | N23: 3500003266 | O23: — | P23: — | Q23: — | R23: PO Released
A24: 20 | B24: — | C24: Sieve Brass Frame 20 cm × 45 microns | D24: — | E24: Sai Krishna | F24: 46245 | G24: 1 | H24: NOS | I24: — | J24: — | K24: 2300003391 | L24: 130 | M24: 1350 | N24: 3500003266 | O24: — | P24: — | Q24: — | R24: PO Released
A25: 21 | B25: — | C25: Pan and Cover for 20 cm Sieves | D25: — | E25: Sai Krishna | F25: 46245 | G25: 1 | H25: NOS | I25: — | J25: — | K25: 2300003391 | L25: 140 | M25: 675 | N25: 3500003266 | O25: — | P25: — | Q25: — | R25: PO Released
A26: 22 | B26: — | C26: Mortar Mixer – 5 Liter | D26: — | E26: Hobart | F26: 46295 | G26: 1 | H26: NOS | I26: — | J26: — | K26: 2300003391 | L26: 150 | M26: 500000 | N26: — | O26: — | P26: — | Q26: — | R26: Commercial Negotiation
A27: 23 | B27: — | C27: Mortar Mixer – 20 Liter | D27: — | E27: Mecons | F27: 46325 | G27: 1 | H27: NOS | I27: — | J27: — | K27: 2300003391 | L27: 160 | M27: 372000 | N27: — | O27: — | P27: — | Q27: — | R27: In Approval
A28: 24 | B28: — | C28: Concrete Grinding Machine | D28: — | E28: U Test | F28: 46341 | G28: 1 | H28: NOS | I28: — | J28: — | K28: 2300003391 | L28: 180 | M28: — | N28: — | O28: — | P28: — | Q28: — | R28: Commercial Negotiation
A29: 25 | B29: — | C29: Automatic Vicat Apparatus | D29: — | E29: Chirayu / Controls | F29: 46280 | G29: 1 | H29: NOS | I29: — | J29: — | K29: 2300003391 | L29: 190 | M29: 572292 | N29: — | O29: — | P29: — | Q29: — | R29: In Approval
A30: 26 | B30: — | C30: Slump Test Accessories | D30: — | E30: Sai Krishna | F30: 46245 | G30: 1 | H30: NOS | I30: — | J30: — | K30: 2300003391 | L30: 200 | M30: 2200 | N30: 3500003266 | O30: — | P30: — | Q30: — | R30: PO Released
A31: 27 | B31: — | C31: Mortar Flow Table Accessories | D31: — | E31: Sai Krishna | F31: 46245 | G31: 1 | H31: NOS | I31: — | J31: — | K31: 2300003391 | L31: 210 | M31: 13050 | N31: 3500003266 | O31: — | P31: — | Q31: — | R31: PO Released
A32: 28 | B32: — | C32: J Ring Apparatus | D32: — | E32: Sai Krishna | F32: 46245 | G32: 1 | H32: NOS | I32: — | J32: — | K32: 2300003391 | L32: 230 | M32: 9450 | N32: 3500003266 | O32: — | P32: — | Q32: — | R32: PO Released
A33: 29 | B33: — | C33: L Box Apparatus | D33: — | E33: Sai Krishna | F33: 46245 | G33: 1 | H33: NOS | I33: — | J33: — | K33: 2300003391 | L33: 240 | M33: 10350 | N33: 3500003266 | O33: — | P33: — | Q33: — | R33: PO Released
A34: 30 | B34: — | C34: U Box Test Apparatus | D34: — | E34: Sai Krishna | F34: 46245 | G34: 1 | H34: NOS | I34: — | J34: — | K34: 2300003391 | L34: 250 | M34: 9800 | N34: 3500003266 | O34: — | P34: — | Q34: — | R34: PO Released
